widgetsnbextension/__init__.py
widgetsnbextension/_version.py
widgetsnbextension/static/extension.js
widgetsnbextension/static/extension.js.LICENSE.txt
widgetsnbextension/static/extension.js.map
widgetsnbextension-4.0.12.data/data/etc/jupyter/nbconfig/notebook.d/widgetsnbextension.json
widgetsnbextension-4.0.12.data/data/share/jupyter/nbextensions/jupyter-js-widgets/extension.js
widgetsnbextension-4.0.12.data/data/share/jupyter/nbextensions/jupyter-js-widgets/extension.js.LICENSE.txt
widgetsnbextension-4.0.12.data/data/share/jupyter/nbextensions/jupyter-js-widgets/extension.js.map
widgetsnbextension-4.0.12.dist-info/LICENSE
widgetsnbextension-4.0.12.dist-info/METADATA
widgetsnbextension-4.0.12.dist-info/WHEEL
widgetsnbextension-4.0.12.dist-info/top_level.txt
widgetsnbextension-4.0.12.dist-info/RECORD
