Metadata-Version: 2.1
Name: widgetsnbextension
Version: 4.0.12
Summary: Jupyter interactive widgets for Jupyter Notebook
Home-page: http://jupyter.org
Author: Jupyter Development Team
Author-email: jupyter@googlegroups.com
License: BSD 3-Clause License
Keywords: Interactive,Interpreter,Shell,Web,notebook,widgets,Jupyter
Platform: Linux
Platform: Mac OS X
Platform: Windows
Classifier: Intended Audience :: Developers
Classifier: Intended Audience :: System Administrators
Classifier: Intended Audience :: Science/Research
Classifier: License :: OSI Approved :: BSD License
Classifier: Programming Language :: Python
Classifier: Programming Language :: Python :: 3
Classifier: Programming Language :: Python :: 3.7
Classifier: Programming Language :: Python :: 3.8
Classifier: Programming Language :: Python :: 3.9
Classifier: Programming Language :: Python :: 3.10
Classifier: Programming Language :: Python :: 3.11
Classifier: Programming Language :: Python :: 3 :: Only
Classifier: Framework :: Jupyter
Requires-Python: >=3.7
License-File: LICENSE
